mseep_rmcp-0.3.3.dist-info/licenses/LICENSE
rmcp/__init__.py
rmcp/cli.py
rmcp/r_integration.py
rmcp/core/__init__.py
rmcp/core/context.py
rmcp/core/schemas.py
rmcp/core/server.py
rmcp/r_assets/__init__.py
rmcp/registries/__init__.py
rmcp/registries/prompts.py
rmcp/registries/resources.py
rmcp/registries/tools.py
rmcp/scripts/__init__.py
rmcp/security/__init__.py
rmcp/security/vfs.py
rmcp/tools/descriptive.py
rmcp/tools/econometrics.py
rmcp/tools/fileops.py
rmcp/tools/machine_learning.py
rmcp/tools/regression.py
rmcp/tools/statistical_tests.py
rmcp/tools/timeseries.py
rmcp/tools/transforms.py
rmcp/tools/visualization.py
rmcp/transport/__init__.py
rmcp/transport/base.py
rmcp/transport/jsonrpc.py
rmcp/transport/stdio.py
mseep_rmcp-0.3.3.dist-info/METADATA
mseep_rmcp-0.3.3.dist-info/WHEEL
mseep_rmcp-0.3.3.dist-info/entry_points.txt
mseep_rmcp-0.3.3.dist-info/top_level.txt
mseep_rmcp-0.3.3.dist-info/RECORD
